afire/__init__.py
afire/__main__.py
afire/completion.py
afire/completion_test.py
afire/console/README.md
afire/console/__init__.py
afire/console/console_attr.py
afire/console/console_attr_os.py
afire/console/console_io.py
afire/console/console_pager.py
afire/console/encoding.py
afire/console/files.py
afire/console/platforms.py
afire/console/text.py
afire/core.py
afire/core_test.py
afire/custom_descriptions.py
afire/custom_descriptions_test.py
afire/decorators.py
afire/decorators_test.py
afire/docstrings.py
afire/docstrings_fuzz_test.py
afire/docstrings_test.py
afire/fire_import_test.py
afire/fire_test.py
afire/formatting.py
afire/formatting_test.py
afire/formatting_windows.py
afire/helptext.py
afire/helptext_test.py
afire/inspectutils.py
afire/inspectutils_test.py
afire/interact.py
afire/interact_test.py
afire/main_test.py
afire/parser.py
afire/parser_fuzz_test.py
afire/parser_test.py
afire/test_components.py
afire/test_components_bin.py
afire/test_components_py3.py
afire/test_components_test.py
afire/testutils.py
afire/testutils_test.py
afire/trace.py
afire/trace_test.py
afire/value_types.py
afire-1.1.0.dist-info/LICENSE
afire-1.1.0.dist-info/METADATA
afire-1.1.0.dist-info/WHEEL
afire-1.1.0.dist-info/RECORD
