Metadata-Version: 2.1
Name: afire
Version: 1.1.0
Summary: python fire cli with type hint support
License: Apache License Version 2.0
Author: zqqqqz2000
Author-email: zqqqqz2000@sina.cn
Requires-Python: >=3.8,<4.0
Classifier: License :: Other/Proprietary License
Classifier: Programming Language :: Python :: 3
Classifier: Programming Language :: Python :: 3.8
Classifier: Programming Language :: Python :: 3.9
Classifier: Programming Language :: Python :: 3.10
Classifier: Programming Language :: Python :: 3.11
Classifier: Programming Language :: Python :: 3.12
Requires-Dist: six (>=1.16.0,<2.0.0)
Requires-Dist: termcolor (>=2.3.0,<3.0.0)
